cellpose/__init__.py
cellpose/__main__.py
cellpose/cli.py
cellpose/core.py
cellpose/denoise.py
cellpose/dynamics.py
cellpose/export.py
cellpose/io.py
cellpose/metrics.py
cellpose/models.py
cellpose/plot.py
cellpose/train.py
cellpose/transforms.py
cellpose/utils.py
cellpose/version.py
cellpose/vit_sam.py
cellpose/contrib/distributed_segmentation.py
cellpose/gui/gui.py
cellpose/gui/gui3d.py
cellpose/gui/guihelpwindowtext.html
cellpose/gui/guiparts.py
cellpose/gui/guitrainhelpwindowtext.html
cellpose/gui/io.py
cellpose/gui/make_train.py
cellpose/gui/menus.py
cellpose/logo/cellpose.ico
cellpose/logo/logo.png
cellpose-4.0.7.dist-info/licenses/LICENSE
cellpose-4.0.7.dist-info/METADATA
cellpose-4.0.7.dist-info/WHEEL
cellpose-4.0.7.dist-info/entry_points.txt
cellpose-4.0.7.dist-info/top_level.txt
cellpose-4.0.7.dist-info/RECORD
