Metadata-Version: 2.4
Name: cellpose
Version: 4.0.7
Summary: anatomical segmentation algorithm
Home-page: https://github.com/MouseLand/cellpose
Author: Marius Pachitariu and Carsen Stringer
Author-email: stringerc@janelia.hhmi.org
License: BSD
Classifier: Programming Language :: Python :: 3
Classifier: License :: OSI Approved :: BSD License
Classifier: Operating System :: OS Independent
License-File: LICENSE
Requires-Dist: numpy>=1.20.0
Requires-Dist: scipy
Requires-Dist: natsort
Requires-Dist: tifffile
Requires-Dist: tqdm
Requires-Dist: torch>=1.6
Requires-Dist: torchvision
Requires-Dist: opencv-python-headless
Requires-Dist: fastremap
Requires-Dist: imagecodecs
Requires-Dist: roifile
Requires-Dist: fill-voids
Requires-Dist: segment_anything
Provides-Extra: docs
Requires-Dist: sphinx>=3.0; extra == "docs"
Requires-Dist: sphinxcontrib-apidoc; extra == "docs"
Requires-Dist: sphinx_rtd_theme; extra == "docs"
Requires-Dist: sphinx-argparse; extra == "docs"
Provides-Extra: gui
Requires-Dist: pyqtgraph>=0.12.4; extra == "gui"
Requires-Dist: pyqt6; extra == "gui"
Requires-Dist: pyqt6.sip; extra == "gui"
Requires-Dist: qtpy; extra == "gui"
Requires-Dist: superqt; extra == "gui"
Provides-Extra: distributed
Requires-Dist: dask; extra == "distributed"
Requires-Dist: distributed; extra == "distributed"
Requires-Dist: dask_image; extra == "distributed"
Requires-Dist: pyyaml; extra == "distributed"
Requires-Dist: zarr; extra == "distributed"
Requires-Dist: dask_jobqueue; extra == "distributed"
Requires-Dist: bokeh; extra == "distributed"
Requires-Dist: pyarrow; extra == "distributed"
Provides-Extra: bioimageio
Requires-Dist: bioimageio.core; extra == "bioimageio"
Provides-Extra: all
Requires-Dist: pyqtgraph>=0.12.4; extra == "all"
Requires-Dist: pyqt6; extra == "all"
Requires-Dist: pyqt6.sip; extra == "all"
Requires-Dist: qtpy; extra == "all"
Requires-Dist: superqt; extra == "all"
Requires-Dist: dask; extra == "all"
Requires-Dist: distributed; extra == "all"
Requires-Dist: dask_image; extra == "all"
Requires-Dist: pyyaml; extra == "all"
Requires-Dist: zarr; extra == "all"
Requires-Dist: dask_jobqueue; extra == "all"
Requires-Dist: bokeh; extra == "all"
Requires-Dist: pyarrow; extra == "all"
Requires-Dist: nd2; extra == "all"
Requires-Dist: pynrrd; extra == "all"
Requires-Dist: bioimageio.core; extra == "all"
Dynamic: author
Dynamic: author-email
Dynamic: classifier
Dynamic: description
Dynamic: description-content-type
Dynamic: home-page
Dynamic: license
Dynamic: license-file
Dynamic: provides-extra
Dynamic: requires-dist
Dynamic: summary
